CHANGES.txt
LICENSE.txt
MANIFEST.in
README.txt
setup.py
argcmd/__init__.py
argcmd/management/__init__.py
argcmd/management/base.py
argcmd/management/commands/__init__.py
django_argparse_command.egg-info/PKG-INFO
django_argparse_command.egg-info/SOURCES.txt
django_argparse_command.egg-info/dependency_links.txt
django_argparse_command.egg-info/top_level.txt