Metadata-Version: 1.0
Name: django-argparse-command
Version: 0.1.0
Summary: Django Commands using ArgumentParser
Home-page: https://github.com/allanlei/django-argparse-command
Author: Allan Lei
Author-email: allanlei@helveticode.com
License: LICENSE.txt
Keywords: django argparse commands optparse
Platform: UNKNOWN
